steamwebapiclient/__init__.py
steamwebapiclient/client.py
steamwebapiclient/generated_client.py
steamwebapiclient-0.1.0.dist-info/LICENSE.txt
steamwebapiclient-0.1.0.dist-info/METADATA
steamwebapiclient-0.1.0.dist-info/WHEEL
steamwebapiclient-0.1.0.dist-info/top_level.txt
steamwebapiclient-0.1.0.dist-info/RECORD
