Metadata-Version: 2.1
Name: steamwebapiclient
Version: 0.1.0
Summary: A Python client for the Steam Web API
Author: Jasper Bok
Author-email: hello@jasperbok.nl
License: MIT License
Project-URL: Source, https://github.com/jasperbok/steamwebapiclient
Keywords: steam,valve,api
Classifier: Development Status :: 3 - Alpha
Classifier: Intended Audience :: Developers
Classifier: License :: OSI Approved :: MIT License
Classifier: Operating System :: OS Independent
Classifier: Programming Language :: Python :: 3.9
License-File: LICENSE.txt
Requires-Dist: requests
